_libolm.abi3.so
olm/__init__.py
olm/_compat.py
olm/_finalize.py
olm/account.py
olm/group_session.py
olm/pk.py
olm/py.typed
olm/sas.py
olm/session.py
olm/utility.py
python_olm-3.2.16.dist-info/METADATA
python_olm-3.2.16.dist-info/WHEEL
python_olm-3.2.16.dist-info/top_level.txt
python_olm-3.2.16.dist-info/RECORD
