Metadata-Version: 2.1
Name: python-olm
Version: 3.2.16
Summary: python CFFI bindings for the olm cryptographic ratchet library
Author-email: Damir Jelić <poljar@termina.org.uk>
License: Apache-2.0
Project-URL: homepage, https://gitlab.matrix.org/matrix-org/olm/-/tree/master/python
Classifier: License :: OSI Approved :: Apache Software License
Classifier: Topic :: Communications
Requires-Dist: cffi>=1.0.0
